{"Parboiled rice": 721.57, "Raw rice": 650.8, "Idli rice": 414.91, "SVS Oil": 439.55, "Sesame Oil": 53.66, "Vim bar": 25.56, "Sabena": 68.63, "Tamarind": 25.56, "Sago": 1.43, "Poha": 4.59, "Chilli stew": 6.18, "Green Peas": 44.73, "Black chickpeas": 8.73, "Roasted gram": 29.99, "Groundnut": 40.77, "White chickpeas": 42.29, "Vermicelli": 21.08, "Urad dal": 171.99, "Green gram": 90.87, "Toor dal": 274.89, "Bengal gram dal": 27.08, "semolina": 24.88, "Rice flour": 4.23, "Wheat flour": 330.59, "Maida flour": 69.17, "Sugar": 318.81, "Turmeric powder": 8.14, "Chana masala": 1.58, "Biriyani masala": 1.62, "Corn Flour": 10.93, "Vinegar": 3.27, "Coffee powder": 8.36, "Tea powder": 10.21, "Mutton masala": 1.95, "Garam masala": 2.12, "Gram flour": 0.91, "Papadam": 7.62, "Chilli powder": 6.65, "Coriander powder": 25.11, "Garlic pickle": 21.52, "Mango pickle": 15.03, "Ghee": 17.67, "Asafoetida": 7.43, "Cumin": 4.64, "Coriander": 2.12, "Fennel": 0.23, "True cardamom": 1.04, "mustard seed": 6.66, "cashew nut": 4.92, "Poppy Seeds": 1.77, "Fenugreek": 3.46, "Baking soda": 3.76, "Black pepper": 1.92, "Cinnamon": 1.0, "Star Anise": 0.23, "Exo Steel Scrubber": 13.73, "Crystal salt": 177.22, "powdered salt": 35.88, "Pepper powder": 0.42, "Bay leaf": 0.24, "Mung bean": 19.4, "Clove": 1.29, "Jaggery": 20.88, "Rasam powder": 1.04, "Saffron": 0.08, "Soya chunks": 10.82}